{
  "title": "Finding the Best Lighting for Your Bedroom: A Practical Layered Approach",
  "seo_title": "How to Choose Lighting for Bedroom",
  "title_family": "insight_led",
  "seo_title_family": "framework_process",
  "title_candidates": [
    {
      "title": "How to Choose Lighting for Bedroom",
      "family": "framework_process",
      "source": "rules",
      "score": 112.71,
      "seo_score": 125.14,
      "opening": "how to",
      "max_similarity": 0.4,
      "notes": [
        "templated opening"
      ]
    },
    {
      "title": "Finding the Best Lighting for Your Bedroom: a Practical Layered Approach",
      "family": "insight_led",
      "source": "model",
      "score": 109.55,
      "seo_score": 103.45,
      "opening": "finding the",
      "max_similarity": 0.4,
      "notes": [
        "slightly long"
      ]
    },
    {
      "title": "Lighting for Bedroom: A Practical Buying Guide",
      "family": "beginner_friendly",
      "source": "rules",
      "score": 107.75,
      "seo_score": 115.75,
      "opening": "lighting for",
      "max_similarity": 0.667,
      "notes": [
        "close to existing title"
      ]
    },
    {
      "title": "Best Lighting for Bedroom: What to Look For",
      "family": "comparison",
      "source": "rules",
      "score": 101.29,
      "seo_score": 118.86,
      "opening": "best",
      "max_similarity": 0.6,
      "notes": [
        "templated opening",
        "family overused site-wide",
        "opening overused site-wide",
        "close to existing title"
      ]
    },
    {
      "title": "Where to Start with Lighting for Bedroom",
      "family": "outcome_first",
      "source": "rules",
      "score": 100.75,
      "seo_score": 107.75,
      "opening": "where to",
      "max_similarity": 0.6,
      "notes": [
        "close to existing title"
      ]
    },
    {
      "title": "Bedroom Lighting: What Actually Matters",
      "family": "insight_led",
      "source": "rules",
      "score": 97.14,
      "seo_score": 89.43,
      "opening": "bedroom lighting:",
      "max_similarity": 0.167,
      "notes": [
        "weak keyword/topic coverage"
      ]
    },
    {
      "title": "Best Lighting for Bedroom",
      "family": "comparison",
      "source": "keyword",
      "score": 97.0,
      "seo_score": 118.0,
      "opening": "best",
      "max_similarity": 0.429,
      "notes": [
        "too short",
        "templated opening",
        "family overused site-wide",
        "opening overused site-wide"
      ]
    }
  ],
  "slug": "best-lighting-for-bedroom-layered-approach",
  "publish_date": "2026-05-25",
  "published_at": "2026-05-25T12:25:38.570995",
  "meta_description": "Explore practical options for the best lighting in your bedroom with layered techniques. Discover how to choose and style bedroom lighting that balances comfort, function, and design.",
  "permalink": "/mistakes%20%26%20fixes/2026/05/25/best-lighting-for-bedroom-layered-approach/",
  "article_relative_url": "/mistakes%20%26%20fixes/2026/05/25/best-lighting-for-bedroom-layered-approach/",
  "primary_keyword": "best lighting for bedroom",
  "secondary_keywords": [
    "bedroom lighting ideas",
    "bedroom lamp styling ideas",
    "how to layer lighting in bedroom",
    "bedroom lighting mistakes to avoid"
  ],
  "topical_cluster": "bedroom lighting",
  "cluster_name": "bedroom lighting",
  "cluster_keywords": [
    "bedroom lighting ideas",
    "bedroom lamp styling ideas",
    "how to layer lighting in bedroom",
    "bedroom lighting mistakes to avoid",
    "best lighting for bedroom",
    "how to place lamps in bedroom",
    "bedroom lamp placement mistakes to avoid",
    "best lamps for bedroom",
    "bedroom ceiling light ideas",
    "how to choose an overhead light for bedroom",
    "bedroom overhead lighting mistakes to avoid",
    "modern bedroom lighting ideas"
  ],
  "search_intent": "comparison",
  "estimated_reading_time": "8 min read",
  "author_id": "elena_hart",
  "author_name": "Elena Hart",
  "categories": [
    "Mistakes & Fixes"
  ],
  "excerpt": "Explore practical options for the best lighting in your bedroom with layered techniques. Discover how to choose and style bedroom lighting that balances comfort, function, and design.",
  "featured": false,
  "domain_id": "bedrooms",
  "cluster_id": "bedroom_lighting",
  "subtopic_id": "layering",
  "subtopic_name": "layered lighting",
  "angle_id": "best_options",
  "intent_id": "comparison",
  "modifier": "",
  "internal_link_suggestions": [],
  "keywords": [
    "best lighting for bedroom",
    "bedroom lighting ideas",
    "bedroom lamp styling ideas",
    "how to layer lighting in bedroom",
    "bedroom lighting mistakes to avoid"
  ],
  "hero_image_prompt": "Create a hero image for the article 'Finding the Best Lighting for Your Bedroom: A Practical Layered Approach'. Show a clean comparison framing that expresses 'bedroom lighting' in a magazine-worthy but believable way. Show a strong option category clearly, with a refined but useful editorial feel. Prioritize one memorable focal point, clear spatial depth, and an image that feels editorial rather than staged for ecommerce. Style direction: clean, sculptural, modern editorial restraint. Visual language: criteria-led, option-aware, and polished enough to support recommendation content. Room context: bedroom. Lighting: clear daylight with crisp shadow definition. Palette: soft white, black accents, stone, pale oak. Subject emphasis: light source, glow quality, and how the fixture shapes the mood of the room. Primary composition: clean comparison framing. Occasional variation: object-forward editorial crop. Medium: editorial interior photography. Constraints: realistic materials, no text, no logos, no people, no artificial collage effects. Keep the architecture believable and the furniture layout realistic for a real home. Do not duplicate the main focal furnishing unless the prompt clearly calls for a shared or twin-room setup. Avoid mirrored, side-by-side, or repeated hero objects that make the room read as AI-generated. Show one primary bed only, not two different beds side-by-side. If bedside pieces appear, they should support a single coherent bedroom layout. If multiple pieces appear, they should read as one coherent styled room or one clearly curated comparison vignette, not duplicated room setups.. Editorial interior photography, natural daylight, realistic materials, no text, no logos, no people.",
  "section_image_prompts": [
    "Create section image 1 for the article 'Finding the Best Lighting for Your Bedroom: A Practical Layered Approach'. Focus on 'Defining the Essential Criteria for Bedroom Lighting'. Use a room shot led by the lighting statement. Let the main emphasis be fixture form. Highlight material differences. Differentiate option types, materials, or use cases visually. The image should clearly support this specific section rather than repeat the hero image. Vary focal distance, crop, and visual weight so the image set feels intentionally diverse. Style direction: clean, sculptural, modern editorial restraint. Visual language: criteria-led, option-aware, and polished enough to support recommendation content. Room context: bedroom. Lighting: clear daylight with crisp shadow definition. Palette: soft white, black accents, stone, pale oak. Subject emphasis: light source, glow quality, and how the fixture shapes the mood of the room. Primary composition: ambient glow crop. Occasional variation: object-forward editorial crop. Medium: editorial interior photography. Constraints: realistic materials, no text, no logos, no people, no artificial collage effects. Keep the architecture believable and the furniture layout realistic for a real home. Do not duplicate the main focal furnishing unless the prompt clearly calls for a shared or twin-room setup. Avoid mirrored, side-by-side, or repeated hero objects that make the room read as AI-generated. Show one primary bed only, not two different beds side-by-side. If bedside pieces appear, they should support a single coherent bedroom layout. If multiple pieces appear, they should read as one coherent styled room or one clearly curated comparison vignette, not duplicated room setups.. Editorial interior photography, natural daylight, realistic materials, no text, no logos, no people.",
    "Create section image 2 for the article 'Finding the Best Lighting for Your Bedroom: A Practical Layered Approach'. Focus on 'Bedside Lamps That Combine Style and Functionality'. Use a fixture detail close-up with surrounding materials. Let the main emphasis be light quality. Highlight finish options. Differentiate option types, materials, or use cases visually. The image should clearly support this specific section rather than repeat the hero image. Vary focal distance, crop, and visual weight so the image set feels intentionally diverse. Style direction: clean, sculptural, modern editorial restraint. Visual language: criteria-led, option-aware, and polished enough to support recommendation content. Room context: bedroom. Lighting: clear daylight with crisp shadow definition. Palette: soft white, black accents, stone, pale oak. Subject emphasis: light source, glow quality, and how the fixture shapes the mood of the room. Primary composition: eye-level corner shot. Occasional variation: clean comparison framing. Medium: editorial interior photography. Constraints: realistic materials, no text, no logos, no people, no artificial collage effects. Keep the architecture believable and the furniture layout realistic for a real home. Do not duplicate the main focal furnishing unless the prompt clearly calls for a shared or twin-room setup. Avoid mirrored, side-by-side, or repeated hero objects that make the room read as AI-generated. Show one primary bed only, not two different beds side-by-side. If bedside pieces appear, they should support a single coherent bedroom layout. If multiple pieces appear, they should read as one coherent styled room or one clearly curated comparison vignette, not duplicated room setups. For detail-driven images, prefer a tight crop of one believable setup instead of widening into multiple duplicated furniture groupings.. Editorial interior photography, natural daylight, realistic materials, no text, no logos, no people.",
    "Create section image 3 for the article 'Finding the Best Lighting for Your Bedroom: A Practical Layered Approach'. Focus on 'Comparing Pendant Lights and Wall Sconces for Ambient Layering'. Use a functional reading, bedside, or task-lighting corner. Let the main emphasis be ambient mood. Highlight style-fit signals. Differentiate option types, materials, or use cases visually. The image should clearly support this specific section rather than repeat the hero image. Vary focal distance, crop, and visual weight so the image set feels intentionally diverse. Style direction: clean, sculptural, modern editorial restraint. Visual language: criteria-led, option-aware, and polished enough to support recommendation content. Room context: bedroom. Lighting: clear daylight with crisp shadow definition. Palette: soft white, black accents, stone, pale oak. Subject emphasis: light source, glow quality, and how the fixture shapes the mood of the room. Primary composition: category-led vignette. Occasional variation: clean comparison framing. Medium: editorial interior photography. Constraints: realistic materials, no text, no logos, no people, no artificial collage effects. Keep the architecture believable and the furniture layout realistic for a real home. Do not duplicate the main focal furnishing unless the prompt clearly calls for a shared or twin-room setup. Avoid mirrored, side-by-side, or repeated hero objects that make the room read as AI-generated. Show one primary bed only, not two different beds side-by-side. If bedside pieces appear, they should support a single coherent bedroom layout. If multiple pieces appear, they should read as one coherent styled room or one clearly curated comparison vignette, not duplicated room setups.. Editorial interior photography, natural daylight, realistic materials, no text, no logos, no people.",
    "Create section image 4 for the article 'Finding the Best Lighting for Your Bedroom: A Practical Layered Approach'. Focus on 'Matching Lighting Choices to Bedroom Size and Layout'. Use a ambient glow shot showing atmosphere. Let the main emphasis be task lighting function. Highlight material differences. Differentiate option types, materials, or use cases visually. The image should clearly support this specific section rather than repeat the hero image. Vary focal distance, crop, and visual weight so the image set feels intentionally diverse. Style direction: clean, sculptural, modern editorial restraint. Visual language: criteria-led, option-aware, and polished enough to support recommendation content. Room context: bedroom. Lighting: clear daylight with crisp shadow definition. Palette: soft white, black accents, stone, pale oak. Subject emphasis: light source, glow quality, and how the fixture shapes the mood of the room. Primary composition: category-led vignette. Occasional variation: clean comparison framing. Medium: editorial interior photography. Constraints: realistic materials, no text, no logos, no people, no artificial collage effects. Keep the architecture believable and the furniture layout realistic for a real home. Do not duplicate the main focal furnishing unless the prompt clearly calls for a shared or twin-room setup. Avoid mirrored, side-by-side, or repeated hero objects that make the room read as AI-generated. Show one primary bed only, not two different beds side-by-side. If bedside pieces appear, they should support a single coherent bedroom layout. If multiple pieces appear, they should read as one coherent styled room or one clearly curated comparison vignette, not duplicated room setups.. Editorial interior photography, natural daylight, realistic materials, no text, no logos, no people.",
    "Create section image 5 for the article 'Finding the Best Lighting for Your Bedroom: A Practical Layered Approach'. Focus on 'Confident Buying Tips to Narrow Your Bedroom Lighting Options'. Use a styled composition showing the fixture integrated into the room. Let the main emphasis be style compatibility. Highlight finish options. Differentiate option types, materials, or use cases visually. The image should clearly support this specific section rather than repeat the hero image. Vary focal distance, crop, and visual weight so the image set feels intentionally diverse. Style direction: clean, sculptural, modern editorial restraint. Visual language: criteria-led, option-aware, and polished enough to support recommendation content. Room context: bedroom. Lighting: clear daylight with crisp shadow definition. Palette: soft white, black accents, stone, pale oak. Subject emphasis: light source, glow quality, and how the fixture shapes the mood of the room. Primary composition: object-forward editorial crop. Occasional variation: clean comparison framing. Medium: editorial interior photography. Constraints: realistic materials, no text, no logos, no people, no artificial collage effects. Keep the architecture believable and the furniture layout realistic for a real home. Do not duplicate the main focal furnishing unless the prompt clearly calls for a shared or twin-room setup. Avoid mirrored, side-by-side, or repeated hero objects that make the room read as AI-generated. Show one primary bed only, not two different beds side-by-side. If bedside pieces appear, they should support a single coherent bedroom layout. If multiple pieces appear, they should read as one coherent styled room or one clearly curated comparison vignette, not duplicated room setups.. Editorial interior photography, natural daylight, realistic materials, no text, no logos, no people."
  ],
  "hero_image_path": "/assets/img/best-lighting-for-bedroom-layered-approach/hero.png",
  "hero_image_alt": "Finding the Best Lighting for Your Bedroom: A Practical Layered Approach interior design inspiration",
  "section_image_paths": [
    "/assets/img/best-lighting-for-bedroom-layered-approach/section-1.png",
    "/assets/img/best-lighting-for-bedroom-layered-approach/section-2.png",
    "/assets/img/best-lighting-for-bedroom-layered-approach/section-3.png",
    "/assets/img/best-lighting-for-bedroom-layered-approach/section-4.png",
    "/assets/img/best-lighting-for-bedroom-layered-approach/section-5.png"
  ],
  "section_image_alts": [
    "Finding the Best Lighting for Your Bedroom: A Practical Layered Approach section 1 interior styling detail",
    "Finding the Best Lighting for Your Bedroom: A Practical Layered Approach section 2 interior styling detail",
    "Finding the Best Lighting for Your Bedroom: A Practical Layered Approach section 3 interior styling detail",
    "Finding the Best Lighting for Your Bedroom: A Practical Layered Approach section 4 interior styling detail",
    "Finding the Best Lighting for Your Bedroom: A Practical Layered Approach section 5 interior styling detail"
  ],
  "pinterest_titles": [
    "How to Layer Bedroom Lighting for a Comfortable, Stylish Space",
    "Best Bedroom Lighting Ideas for Every Room Size and Style",
    "Choosing the Right Lamps and Fixtures for Bedroom Layering",
    "Avoid These Bedroom Lighting Mistakes and Get It Right",
    "Confident Bedroom Lighting Choices That Blend Function & Mood"
  ],
  "pinterest_descriptions": [
    "Discover simple yet effective ways to layer lighting in your bedroom to create cozy, functional, and beautiful spaces with practical styling tips anyone can use.",
    "Explore versatile bedroom lighting ideas that balance ambient, task, and accent lights for every bedroom size and design style.",
    "Learn how to pick bedside lamps, overhead fixtures, and accent lighting that work together to enhance your bedroom's look and feel.",
    "Avoid common bedroom lighting mistakes with clear advice on fixture placement, bulb choice, and setting the right mood through layering.",
    "Take the guesswork out of bedroom lighting by understanding how to combine price points and light types for rooms that feel warm and well-planned."
  ],
  "visual_direction": {
    "family_id": "crisp_modern",
    "mood": "clean, sculptural, modern editorial restraint",
    "lighting": "clear daylight with crisp shadow definition",
    "palette": "soft white, black accents, stone, pale oak",
    "intent_id": "comparison",
    "profile_id": "comparison",
    "shot_library_id": "lighting"
  },
  "image_prompt_diagnostics": {
    "sameness_warnings": [
      "Recent-article sameness warning: the hero prompt is very close to multiple recent hero prompts."
    ],
    "recent_articles_checked": 12
  },
  "affiliate_products": [],
  "monetization_profile": {
    "profile_id": "commercial_strong",
    "name": "Commercial Strong",
    "description": "Stronger but still editorial monetization for option-led and recommendation articles.",
    "min_products_to_enable": 3,
    "max_products": 4,
    "max_inline_links": 4,
    "preferred_section_indexes": [
      1,
      2,
      4,
      5
    ],
    "shop_block_enabled": true,
    "shop_block_kicker": "Recommended Picks",
    "shop_block_heading": "Best Picks to Consider",
    "shop_button_label": "See Option",
    "prompt_guidance": "This article can support stronger product integration, but keep the recommendations tied to clear selection criteria and real reader needs.",
    "inline_sentence_templates": [
      "If you want a ready-made option in this category, [{title}]({affiliate_url}) is worth a look.",
      "A strong pick here is [{title}]({affiliate_url}) if this is the direction that fits your room best."
    ]
  },
  "faq_items": [
    {
      "question": "What color temperature is best for bedroom lighting?",
      "answer": "Warm whites between 2700K and 3000K are ideal as they create a cozy and relaxing atmosphere conducive to winding down."
    },
    {
      "question": "How many layers of lighting should a bedroom have?",
      "answer": "Typically, three layers—ambient, task, and accent—cover all needs and moods effectively without cluttering the space."
    },
    {
      "question": "Can I use only bedside lamps instead of ceiling lighting?",
      "answer": "While bedside lamps provide focused light, having some ambient ceiling light helps avoid an overly dim room and provides balance."
    },
    {
      "question": "How do I avoid bedroom lighting mistakes?",
      "answer": "Avoid harsh overhead lighting without dimming, mismatched fixture scale, and neglecting to layer your lights for different activities."
    },
    {
      "question": "Are smart bulbs worth it for bedroom lighting?",
      "answer": "Smart bulbs offer great flexibility with dimming and color temperature adjustments, making them a practical upgrade for layered lighting setups. Choosing the best lighting for a bedroom confidently comes down to understanding your room’s size, style, and how you use the space. Layered lighting—combining ambient, task, and accent sources—is the key to blending function and visual comfort. Start by defining your needs clearly, then mix in bedside lamps, overhead options, and the right finishes to build a soft, flexible glow that feels as good as it looks. This approach helps your bedroom become a calm, well-lit refuge that adapts gracefully from morning routines to nighttime relaxation."
    }
  ],
  "post_path": "/home/runner/work/Project-Blog/Project-Blog/_posts/2026-05-25-best-lighting-for-bedroom-layered-approach.md",
  "updated_at": "2026-05-25T12:25:38.778109"
}